Workbook

Sheet Attendance_Sheet
B2: Month | C2: Year | D2: ="Fully Automatic Attendance Sheet - "&B3&" "&C3 -> Fully Automatic Attendance Sheet - June 2026 | AI2: Made by Shashank Masih Toppo
B3: June | C3: 2026
B4: =DATEVALUE("1"&B3&C3) -> 46174 | C4: =EOMONTH(B4,0) -> 46203
B5: EMP_ID | C5: EMP_NAME | D5: =B4 -> 46174 | E5: =IF(D5<$C$4,D5+1," ") -> 46175 | F5: =IF(E5<$C$4,E5+1," ") -> 46176 | G5: =IF(F5<$C$4,F5+1," ") -> 46177 | H5: =IF(G5<$C$4,G5+1," ") -> 46178 | I5: =IF(H5<$C$4,H5+1," ") -> 46179 | J5: =IF(I5<$C$4,I5+1," ") -> 46180 | K5: =IF(J5<$C$4,J5+1," ") -> 46181 | L5: =IF(K5<$C$4,K5+1," ") -> 46182 | ... AH5: =IF(AG5<$C$4,AG5+1," ") | AI5: Total Days | AJ5: Present | AK5: Holiday | AL5: Week Off | AM5: Absent
D6: =TEXT(D5,"DDD") -> Mon | E6: =TEXT(E5,"DDD") -> Tue | F6: =TEXT(F5,"DDD") -> Wed | G6: =TEXT(G5,"DDD") -> Thu | H6: =TEXT(H5,"DDD") -> Fri | I6: =TEXT(I5,"DDD") -> Sat | J6: =TEXT(J5,"DDD") -> Sun | K6: =TEXT(K5,"DDD") -> Mon | ... AH6: =TEXT(AH5,"DDD")
B8: EMP001 | C8: Aarav Sharma | D8: P | E8: P | F8: P | G8: P | H8: P | I8: P | K8: A | L8: P | M8: P | N8: P | O8: P | P8: A | R8: P | S8: P | T8: P | U8: P | V8: P | W8: P | Y8: P | Z8: P | AA8: P | AB8: P | AC8: P | AD8: P | AF8: P | AG8: P | AI8: =COUNT(D$5:AH$5) -> 30 | AJ8: =COUNTIF($D8:$AH8,"P") -> 24 | AK8: =COUNTIF($D8:$AH8,"H") -> 0 | AL8: =COUNTIF(D$6:AH$7,"Sun") -> 4 | AM8: =COUNTIF($D8:$AH8,"A") -> 2
B9: EMP002 | C9: Priya Singh | D9: P | E9: P | F9: A | G9: P | H9: A | I9: P | K9: P | L9: P | M9: A | N9: P | O9: A | P9: P | R9: A | S9: P | T9: P | U9: P | V9: P | W9: P | Y9: A | Z9: P | AA9: A | AB9: P | AC9: A | AD9: P | AF9: P | AG9: P | AI9: =COUNT(D$5:AH$5) -> 30 | AJ9: =COUNTIF($D9:$AH9,"P") -> 18 | AK9: =COUNTIF($D9:$AH9,"H") -> 0 | AL9: =COUNTIF(D$6:AH$7,"Sun") -> 4 | AM9: =COUNTIF($D9:$AH9,"A") -> 8
B10: EMP003 | C10: Rahul Verma | D10: A | E10: P | F10: P | G10: P | H10: P | I10: P | K10: A | L10: P | M10: P | N10: P | O10: P | P10: P | R10: P | S10: P | T10: P | U10: A | V10: A | W10: A | Y10: P | Z10: P | AA10: P | AB10: P | AC10: P | AD10: P | AF10: P | AG10: A | AI10: =COUNT(D$5:AH$5) -> 30 | AJ10: =COUNTIF($D10:$AH10,"P") -> 20 | AK10: =COUNTIF($D10:$AH10,"H") -> 0 | AL10: =COUNTIF(D$6:AH$7,"Sun") -> 4 | AM10: =COUNTIF($D10:$AH10,"A") -> 6
B11: EMP004 | C11: Neha Gupta | D11: P | E11: P | F11: P | G11: P | H11: P | I11: P | K11: P | L11: A | M11: P | N11: P | O11: P | P11: A | R11: P | S11: A | T11: P | U11: P | V11: P | W11: P | Y11: P | Z11: P | AA11: P | AB11: P | AC11: P | AD11: P | AF11: P | AG11: P | AI11: =COUNT(D$5:AH$5) -> 30 | AJ11: =COUNTIF($D11:$AH11,"P") -> 23 | AK11: =COUNTIF($D11:$AH11,"H") -> 0 | AL11: =COUNTIF(D$6:AH$7,"Sun") -> 4 | AM11: =COUNTIF($D11:$AH11,"A") -> 3
B12: EMP005 | C12: Vikram Patel | D12: P | E12: P | F12: A | G12: P | H12: P | I12: P | K12: P | L12: P | M12: P | N12: A | O12: A | P12: P | R12: P | S12: P | T12: A | U12: P | V12: P | W12: P | Y12: A | Z12: P | AA12: P | AB12: P | AC12: P | AD12: A | AF12: A | AG12: P | AI12: =COUNT(D$5:AH$5) -> 30 | AJ12: =COUNTIF($D12:$AH12,"P") -> 19 | AK12: =COUNTIF($D12:$AH12,"H") -> 0 | AL12: =COUNTIF(D$6:AH$7,"Sun") -> 4 | AM12: =COUNTIF($D12:$AH12,"A") -> 7
B13: EMP006 | C13: Ananya Roy | D13: P | E13: A | F13: P | G13: P | H13: P | I13: A | K13: P | L13: A | M13: P | N13: P | O13: P | P13: P | R13: A | S13: P | T13: P | U13: P | V13: P | W13: P | Y13: P | Z13: P | AA13: P | AB13: A | AC13: P | AD13: P | AF13: P | AG13: P | AI13: =COUNT(D$5:AH$5) -> 30 | AJ13: =COUNTIF($D13:$AH13,"P") -> 21 | AK13: =COUNTIF($D13:$AH13,"H") -> 0 | AL13: =COUNTIF(D$6:AH$7,"Sun") -> 4 | AM13: =COUNTIF($D13:$AH13,"A") -> 5
B14: EMP007 | C14: Karan Mehta | D14: A | E14: P | F14: P | G14: A | H14: P | I14: P | K14: P | L14: P | M14: P | N14: A | O14: P | P14: P | R14: P | S14: P | T14: P | U14: A | V14: A | W14: A | Y14: P | Z14: A | AA14: P | AB14: P | AC14: P | AD14: A | AF14: P | AG14: A | AI14: =COUNT(D$5:AH$5) -> 30 | AJ14: =COUNTIF($D14:$AH14,"P") -> 17 | AK14: =COUNTIF($D14:$AH14,"H") -> 0 | AL14: =COUNTIF(D$6:AH$7,"Sun") -> 4 | AM14: =COUNTIF($D14:$AH14,"A") -> 9
B15: EMP008 | C15: Sneha Kapoor | D15: P | E15: P | F15: P | G15: P | H15: A | I15: P | K15: A | L15: P | M15: A | N15: P | O15: P | P15: A | R15: P | S15: A | T15: P | U15: P | V15: P | W15: P | Y15: P | Z15: P | AA15: A | AB15: P | AC15: A | AD15: P | AF15: P | AG15: P | AI15: =COUNT(D$5:AH$5) -> 30 | AJ15: =COUNTIF($D15:$AH15,"P") -> 19 | AK15: =COUNTIF($D15:$AH15,"H") -> 0 | AL15: =COUNTIF(D$6:AH$7,"Sun") -> 4 | AM15: =COUNTIF($D15:$AH15,"A") -> 7
B16: EMP009 | C16: Rohan Das | D16: P | E16: A | F16: P | G16: P | H16: P | I16: P | K16: P | L16: P | M16: P | N16: A | O16: P | P16: P | R16: P | S16: P | T16: A | U16: P | V16: P | W16: P | Y16: P | Z16: P | AA16: P | AB16: P | AC16: P | AD16: A | AF16: A | AG16: P | AI16: =COUNT(D$5:AH$5) -> 30 | AJ16: =COUNTIF($D16:$AH16,"P") -> 21 | AK16: =COUNTIF($D16:$AH16,"H") -> 0 | AL16: =COUNTIF(D$6:AH$7,"Sun") -> 4 | AM16: =COUNTIF($D16:$AH16,"A") -> 5
B17: EMP010 | C17: Pooja Nair | D17: P | E17: P | F17: A | G17: P | H17: P | I17: A | K17: P | L17: A | M17: P | N17: P | O17: A | P17: P | R17: A | S17: P | T17: P | U17: A | V17: A | W17: A | Y17: A | Z17: P | AA17: P | AB17: A | AC17: P | AD17: P | AF17: P | AG17: A | AI17: =COUNT(D$5:AH$5) -> 30 | AJ17: =COUNTIF($D17:$AH17,"P") -> 15 | AK17: =COUNTIF($D17:$AH17,"H") -> 0 | AL17: =COUNTIF(D$6:AH$7,"Sun") -> 4 | AM17: =COUNTIF($D17:$AH17,"A") -> 11
B18: EMP011 | C18: Arjun Kumar | D18: P | E18: A | F18: P | G18: P | H18: P | I18: P | K18: P | L18: P | M18: P | N18: P | O18: P | P18: P | R18: P | S18: P | T18: P | U18: P | V18: P | W18: P | Y18: P | Z18: P | AA18: P | AB18: P | AC18: P | AD18: P | AF18: P | AG18: P | AI18: =COUNT(D$5:AH$5) -> 30 | AJ18: =COUNTIF($D18:$AH18,"P") -> 25 | AK18: =COUNTIF($D18:$AH18,"H") -> 0 | AL18: =COUNTIF(D$6:AH$7,"Sun") -> 4 | AM18: =COUNTIF($D18:$AH18,"A") -> 1
B19: EMP012 | C19: Meera Joshi | D19: A | E19: P | F19: P | G19: P | H19: P | I19: P | K19: A | L19: P | M19: P | N19: A | O19: P | P19: A | R19: P | S19: P | T19: A | U19: P | V19: P | W19: P | Y19: P | Z19: P | AA19: P | AB19: P | AC19: P | AD19: A | AF19: A | AG19: P | AI19: =COUNT(D$5:AH$5) -> 30 | AJ19: =COUNTIF($D19:$AH19,"P") -> 19 | AK19: =COUNTIF($D19:$AH19,"H") -> 0 | AL19: =COUNTIF(D$6:AH$7,"Sun") -> 4 | AM19: =COUNTIF($D19:$AH19,"A") -> 7
B20: EMP013 | C20: Aditya Mishra | D20: P | E20: P | F20: A | G20: P | H20: A | I20: P | K20: P | L20: P | M20: P | N20: P | O20: P | P20: P | R20: P | S20: A | T20: P | U20: P | V20: P | W20: P | Y20: A | Z20: P | AA20: A | AB20: P | AC20: P | AD20: P | AF20: P | AG20: P | AI20: =COUNT(D$5:AH$5) -> 30 | AJ20: =COUNTIF($D20:$AH20,"P") -> 21 | AK20: =COUNTIF($D20:$AH20,"H") -> 0 | AL20: =COUNTIF(D$6:AH$7,"Sun") -> 4 | AM20: =COUNTIF($D20:$AH20,"A") -> 5
B34: January
B35: February
B36: March
B37: April
B38: May
B39: June
B40: July
B41: August
B42: September
B43: October
B44: November
B45: December

Sheet Salary_Sheet
A1: ="Fully Automatic Salary Sheet - "&Attendance_Sheet!B3&" "&Attendance_Sheet!C3 -> Fully Automatic Salary Sheet - June 2026 | P1: Made by Shashank Masih Toppo
A4: EMP_ID | B4: EMP_Name | C4: Designation | D4: Basic Salary | E4: Total Days | F4: Attendance(Working Days) | G4: Per Day Salary | H4: Salary (Based on Attendance) | I4: DA (12%) | J4: City | K4: HRA | L4: TA | M4: OT in Hrs. | N4: Overtime Pay | O4: Gross Salary | P4: PF (12%) | Q4: ESI (0.75%) | R4: Net Salary
A5: =Attendance_Sheet!B8 -> EMP001 | B5: =Attendance_Sheet!C8 -> Aarav Sharma | C5: Manager | D5: 65000 | E5: =Attendance_Sheet!AI8 -> 30 | F5: =SUM(Attendance_Sheet!AJ8:AL8) -> 28 | G5: =D5/E5 -> 2166.6667 | H5: =F5*G5 -> 60666.667 | I5: =D5*12% -> 7800 | J5: Metro | K5: =IF(J5="Metro",D5*50%,D5*40%) -> 32500 | L5: 1000 | M5: 10 | N5: =G5/9*M5 -> 2407.4074 | O5: =H5+I5+K5+L5+N5 -> 104374.07 | P5: =D5*12% -> 7800 | Q5: =IF(O5<=21000,O5*0.75%,"N/A") -> N/A | R5: =IF(ISNUMBER(Q5),O5-P5-Q5,O5-P5) -> 96574.074
A6: =Attendance_Sheet!B9 -> EMP002 | B6: =Attendance_Sheet!C9 -> Priya Singh | C6: HR Executive | D6: 42000 | E6: =Attendance_Sheet!AI9 -> 30 | F6: =SUM(Attendance_Sheet!AJ9:AL9) -> 22 | G6: =D6/E6 -> 1400 | H6: =F6*G6 -> 30800 | I6: =D6*12% -> 5040 | J6: Non-Merto | K6: =IF(J6="Metro",D6*50%,D6*40%) -> 16800 | L6: 2000 | M6: 15 | N6: =G6/9*M6 -> 2333.3333 | O6: =H6+I6+K6+L6+N6 -> 56973.333 | P6: =D6*12% -> 5040 | Q6: =IF(O6<=21000,O6*0.75%,"N/A") -> N/A | R6: =IF(ISNUMBER(Q6),O6-P6-Q6,O6-P6) -> 51933.333
A7: =Attendance_Sheet!B10 -> EMP003 | B7: =Attendance_Sheet!C10 -> Rahul Verma | C7: Data Analyst | D7: 50000 | E7: =Attendance_Sheet!AI10 -> 30 | F7: =SUM(Attendance_Sheet!AJ10:AL10) -> 24 | G7: =D7/E7 -> 1666.6667 | H7: =F7*G7 -> 40000 | I7: =D7*12% -> 6000 | J7: Metro | K7: =IF(J7="Metro",D7*50%,D7*40%) -> 25000 | L7: 1000 | M7: 20 | N7: =G7/9*M7 -> 3703.7037 | O7: =H7+I7+K7+L7+N7 -> 75703.704 | P7: =D7*12% -> 6000 | Q7: =IF(O7<=21000,O7*0.75%,"N/A") -> N/A | R7: =IF(ISNUMBER(Q7),O7-P7-Q7,O7-P7) -> 69703.704
A8: =Attendance_Sheet!B11 -> EMP004 | B8: =Attendance_Sheet!C11 -> Neha Gupta | C8: Marketing Executive | D8: 45000 | E8: =Attendance_Sheet!AI11 -> 30 | F8: =SUM(Attendance_Sheet!AJ11:AL11) -> 27 | G8: =D8/E8 -> 1500 | H8: =F8*G8 -> 40500 | I8: =D8*12% -> 5400 | J8: Metro | K8: =IF(J8="Metro",D8*50%,D8*40%) -> 22500 | L8: 3000 | M8: 25 | N8: =G8/9*M8 -> 4166.6667 | O8: =H8+I8+K8+L8+N8 -> 75566.667 | P8: =D8*12% -> 5400 | Q8: =IF(O8<=21000,O8*0.75%,"N/A") -> N/A | R8: =IF(ISNUMBER(Q8),O8-P8-Q8,O8-P8) -> 70166.667
A9: =Attendance_Sheet!B12 -> EMP005 | B9: =Attendance_Sheet!C12 -> Vikram Patel | C9: Sales Executive | D9: 48000 | E9: =Attendance_Sheet!AI12 -> 30 | F9: =SUM(Attendance_Sheet!AJ12:AL12) -> 23 | G9: =D9/E9 -> 1600 | H9: =F9*G9 -> 36800 | I9: =D9*12% -> 5760 | J9: Non-Merto | K9: =IF(J9="Metro",D9*50%,D9*40%) -> 19200 | L9: 2000 | M9: 20 | N9: =G9/9*M9 -> 3555.5556 | O9: =H9+I9+K9+L9+N9 -> 67315.556 | P9: =D9*12% -> 5760 | Q9: =IF(O9<=21000,O9*0.75%,"N/A") -> N/A | R9: =IF(ISNUMBER(Q9),O9-P9-Q9,O9-P9) -> 61555.556
A10: =Attendance_Sheet!B13 -> EMP006 | B10: =Attendance_Sheet!C13 -> Ananya Roy | C10: Accountant | D10: 52000 | E10: =Attendance_Sheet!AI13 -> 30 | F10: =SUM(Attendance_Sheet!AJ13:AL13) -> 25 | G10: =D10/E10 -> 1733.3333 | H10: =F10*G10 -> 43333.333 | I10: =D10*12% -> 6240 | J10: Non-Merto | K10: =IF(J10="Metro",D10*50%,D10*40%) -> 20800 | L10: 1000 | M10: 20 | N10: =G10/9*M10 -> 3851.8519 | O10: =H10+I10+K10+L10+N10 -> 75225.185 | P10: =D10*12% -> 6240 | Q10: =IF(O10<=21000,O10*0.75%,"N/A") -> N/A | R10: =IF(ISNUMBER(Q10),O10-P10-Q10,O10-P10) -> 68985.185
A11: =Attendance_Sheet!B14 -> EMP007 | B11: =Attendance_Sheet!C14 -> Karan Mehta | C11: Business Analyst | D11: 60000 | E11: =Attendance_Sheet!AI14 -> 30 | F11: =SUM(Attendance_Sheet!AJ14:AL14) -> 21 | G11: =D11/E11 -> 2000 | H11: =F11*G11 -> 42000 | I11: =D11*12% -> 7200 | J11: Metro | K11: =IF(J11="Metro",D11*50%,D11*40%) -> 30000 | L11: 3000 | M11: 12 | N11: =G11/9*M11 -> 2666.6667 | O11: =H11+I11+K11+L11+N11 -> 84866.667 | P11: =D11*12% -> 7200 | Q11: =IF(O11<=21000,O11*0.75%,"N/A") -> N/A | R11: =IF(ISNUMBER(Q11),O11-P11-Q11,O11-P11) -> 77666.667
A12: =Attendance_Sheet!B15 -> EMP008 | B12: =Attendance_Sheet!C15 -> Sneha Kapoor | C12: Business Analyst | D12: 60000 | E12: =Attendance_Sheet!AI15 -> 30 | F12: =SUM(Attendance_Sheet!AJ15:AL15) -> 23 | G12: =D12/E12 -> 2000 | H12: =F12*G12 -> 46000 | I12: =D12*12% -> 7200 | J12: Non-Merto | K12: =IF(J12="Metro",D12*50%,D12*40%) -> 24000 | L12: 2000 | M12: 15 | N12: =G12/9*M12 -> 3333.3333 | O12: =H12+I12+K12+L12+N12 -> 82533.333 | P12: =D12*12% -> 7200 | Q12: =IF(O12<=21000,O12*0.75%,"N/A") -> N/A | R12: =IF(ISNUMBER(Q12),O12-P12-Q12,O12-P12) -> 75333.333
A13: =Attendance_Sheet!B16 -> EMP009 | B13: =Attendance_Sheet!C16 -> Rohan Das | C13: Software Engineer | D13: 55000 | E13: =Attendance_Sheet!AI16 -> 30 | F13: =SUM(Attendance_Sheet!AJ16:AL16) -> 25 | G13: =D13/E13 -> 1833.3333 | H13: =F13*G13 -> 45833.333 | I13: =D13*12% -> 6600 | J13: Metro | K13: =IF(J13="Metro",D13*50%,D13*40%) -> 27500 | L13: 1000 | M13: 25 | N13: =G13/9*M13 -> 5092.5926 | O13: =H13+I13+K13+L13+N13 -> 86025.926 | P13: =D13*12% -> 6600 | Q13: =IF(O13<=21000,O13*0.75%,"N/A") -> N/A | R13: =IF(ISNUMBER(Q13),O13-P13-Q13,O13-P13) -> 79425.926
A14: =Attendance_Sheet!B17 -> EMP010 | B14: =Attendance_Sheet!C17 -> Pooja Nair | C14: Finance Executive Intern. | D14: 15000 | E14: =Attendance_Sheet!AI17 -> 30 | F14: =SUM(Attendance_Sheet!AJ17:AL17) -> 19 | G14: =D14/E14 -> 500 | H14: =F14*G14 -> 9500 | I14: =D14*12% -> 1800 | J14: Metro | K14: =IF(J14="Metro",D14*50%,D14*40%) -> 7500 | L14: 1000 | M14: 20 | N14: =G14/9*M14 -> 1111.1111 | O14: =H14+I14+K14+L14+N14 -> 20911.111 | P14: =D14*12% -> 1800 | Q14: =IF(O14<=21000,O14*0.75%,"N/A") -> 156.83333 | R14: =IF(ISNUMBER(Q14),O14-P14-Q14,O14-P14) -> 18954.278
A15: =Attendance_Sheet!B18 -> EMP011 | B15: =Attendance_Sheet!C18 -> Arjun Kumar | C15: Marketing Executive Intern. | D15: 10000 | E15: =Attendance_Sheet!AI18 -> 30 | F15: =SUM(Attendance_Sheet!AJ18:AL18) -> 29 | G15: =D15/E15 -> 333.33333 | H15: =F15*G15 -> 9666.6667 | I15: =D15*12% -> 1200 | J15: Metro | K15: =IF(J15="Metro",D15*50%,D15*40%) -> 5000 | L15: 2000 | M15: 10 | N15: =G15/9*M15 -> 370.37037 | O15: =H15+I15+K15+L15+N15 -> 18237.037 | P15: =D15*12% -> 1200 | Q15: =IF(O15<=21000,O15*0.75%,"N/A") -> 136.77778 | R15: =IF(ISNUMBER(Q15),O15-P15-Q15,O15-P15) -> 16900.259
A16: =Attendance_Sheet!B19 -> EMP012 | B16: =Attendance_Sheet!C19 -> Meera Joshi | C16: Sales Executive Intern. | D16: 10000 | E16: =Attendance_Sheet!AI19 -> 30 | F16: =SUM(Attendance_Sheet!AJ19:AL19) -> 23 | G16: =D16/E16 -> 333.33333 | H16: =F16*G16 -> 7666.6667 | I16: =D16*12% -> 1200 | J16: Non-Merto | K16: =IF(J16="Metro",D16*50%,D16*40%) -> 4000 | L16: 2000 | M16: 23 | N16: =G16/9*M16 -> 851.85185 | O16: =H16+I16+K16+L16+N16 -> 15718.519 | P16: =D16*12% -> 1200 | Q16: =IF(O16<=21000,O16*0.75%,"N/A") -> 117.88889 | R16: =IF(ISNUMBER(Q16),O16-P16-Q16,O16-P16) -> 14400.63
A17: =Attendance_Sheet!B20 -> EMP013 | B17: =Attendance_Sheet!C20 -> Aditya Mishra | C17: Sales Executive Intern. | D17: 10000 | E17: =Attendance_Sheet!AI20 -> 30 | F17: =SUM(Attendance_Sheet!AJ20:AL20) -> 25 | G17: =D17/E17 -> 333.33333 | H17: =F17*G17 -> 8333.3333 | I17: =D17*12% -> 1200 | J17: Metro | K17: =IF(J17="Metro",D17*50%,D17*40%) -> 5000 | L17: 3000 | M17: 15 | N17: =G17/9*M17 -> 555.55556 | O17: =H17+I17+K17+L17+N17 -> 18088.889 | P17: =D17*12% -> 1200 | Q17: =IF(O17<=21000,O17*0.75%,"N/A") -> 135.66667 | R17: =IF(ISNUMBER(Q17),O17-P17-Q17,O17-P17) -> 16753.222

Sheet Salary_Slip
B2: XYZ Services Private Limited
C3: Prepared By Shashank Masih Toppo
C4: Civil Lines Business Centre, Mahatma Gandhi Marg, Civil Lines, Prayagraj, Uttar Pradesh 211001, India
C5: ="Salary Slip For The Month Of - "&Attendance_Sheet!B3&" "&Attendance_Sheet!C3 -> Salary Slip For The Month Of - June 2026
C7: Employee Details | E7: Salary Details
C8: EMP_ID | D8: EMP001 | E8: Total Days | F8: =VLOOKUP($D$8,Salary_Sheet!$A$4:$R$17,MATCH(E8,Salary_Sheet!$A$4:$R$4,0),FALSE) -> 30
C9: EMP_Name | D9: =VLOOKUP($D$8,Salary_Sheet!$A$4:$R$17,MATCH(C9,Salary_Sheet!$A$4:$R$4,0),FALSE) -> Aarav Sharma | E9: Attendance(Working Days) | F9: =VLOOKUP($D$8,Salary_Sheet!$A$4:$R$17,MATCH(E9,Salary_Sheet!$A$4:$R$4,0),FALSE) -> 28
C10: Designation | D10: =VLOOKUP($D$8,Salary_Sheet!$A$4:$R$17,MATCH(C10,Salary_Sheet!$A$4:$R$4,0),FALSE) -> Manager | E10: Salary Slip Print Date | F10: =TODAY() -> 46178
C12: Basic Salary | E12: =VLOOKUP($D$8,Salary_Sheet!$A$4:$R$17,MATCH(C12,Salary_Sheet!$A$4:$R$4,0),FALSE) -> 65000
C14: Earnings | E14: Deductions
C15: Salary (Based on Attendance) | D15: =VLOOKUP($D$8,Salary_Sheet!$A$4:$R$17,MATCH(C15,Salary_Sheet!$A$4:$R$4,0),FALSE) -> 60666.667 | E15: PF (12%) | F15: =VLOOKUP($D$8,Salary_Sheet!$A$4:$R$17,MATCH(E15,Salary_Sheet!$A$4:$R$4,0),FALSE) -> 7800
C16: DA (12%) | D16: =VLOOKUP($D$8,Salary_Sheet!$A$4:$R$17,MATCH(C16,Salary_Sheet!$A$4:$R$4,0),FALSE) -> 7800 | E16: ESI (0.75%) | F16: =VLOOKUP($D$8,Salary_Sheet!$A$4:$R$17,MATCH(E16,Salary_Sheet!$A$4:$R$4,0),FALSE) -> N/A
C17: HRA | D17: =VLOOKUP($D$8,Salary_Sheet!$A$4:$R$17,MATCH(C17,Salary_Sheet!$A$4:$R$4,0),FALSE) -> 32500 | E17: Loan | F17: =IFERROR(VLOOKUP($D$8,Salary_Sheet!$A$4:$R$17,MATCH(E17,Salary_Sheet!$A$4:$R$4,0),FALSE),0) -> 0
C18: TA | D18: =VLOOKUP($D$8,Salary_Sheet!$A$4:$R$17,MATCH(C18,Salary_Sheet!$A$4:$R$4,0),FALSE) -> 1000 | E18: Tax | F18: =IFERROR(VLOOKUP($D$8,Salary_Sheet!$A$4:$R$17,MATCH(E18,Salary_Sheet!$A$4:$R$4,0),FALSE),0) -> 0
C19: Overtime Pay | D19: =VLOOKUP($D$8,Salary_Sheet!$A$4:$R$17,MATCH(C19,Salary_Sheet!$A$4:$R$4,0),FALSE) -> 2407.4074
C20: Gross Salary | D20: =SUM(D15:D19) -> 104374.07 | E20: Gross Deduction | F20: =SUM(F15:F18) -> 7800
C22: Net Salary | E22: =D20-F20 -> 96574.074
C24: Employee Signature _________________ | E24: Manger Signature _________________
C26: This is a sample salary slip generated as a part of my personal project.
